odoo8_addon_stock_location_ownership-8.0.0.1.0.99.dev13-py3.8-nspkg.pth
odoo_addons/stock_location_ownership/README.rst
odoo_addons/stock_location_ownership/__init__.py
odoo_addons/stock_location_ownership/__openerp__.py
odoo_addons/stock_location_ownership/i18n/ca.po
odoo_addons/stock_location_ownership/i18n/de.po
odoo_addons/stock_location_ownership/i18n/es.po
odoo_addons/stock_location_ownership/i18n/fr.po
odoo_addons/stock_location_ownership/i18n/hr.po
odoo_addons/stock_location_ownership/i18n/it.po
odoo_addons/stock_location_ownership/i18n/sl.po
odoo_addons/stock_location_ownership/i18n/stock_location_ownership.pot
odoo_addons/stock_location_ownership/i18n/tr.po
odoo_addons/stock_location_ownership/model/__init__.py
odoo_addons/stock_location_ownership/model/stock.py
odoo_addons/stock_location_ownership/static/description/icon.png
odoo_addons/stock_location_ownership/view/stock_view.xml
odoo8_addon_stock_location_ownership-8.0.0.1.0.99.dev13.dist-info/METADATA
odoo8_addon_stock_location_ownership-8.0.0.1.0.99.dev13.dist-info/WHEEL
odoo8_addon_stock_location_ownership-8.0.0.1.0.99.dev13.dist-info/namespace_packages.txt
odoo8_addon_stock_location_ownership-8.0.0.1.0.99.dev13.dist-info/top_level.txt
odoo8_addon_stock_location_ownership-8.0.0.1.0.99.dev13.dist-info/RECORD
